dolomite_se/__init__.py
dolomite_se/read_ranged_summarized_experiment.py
dolomite_se/read_summarized_experiment.py
dolomite_se/save_ranged_summarized_experiment.py
dolomite_se/save_summarized_experiment.py
dolomite_se/utils.py
dolomite_se-0.3.0.dist-info/LICENSE.txt
dolomite_se-0.3.0.dist-info/METADATA
dolomite_se-0.3.0.dist-info/WHEEL
dolomite_se-0.3.0.dist-info/top_level.txt
dolomite_se-0.3.0.dist-info/RECORD
